datus_snowflake/__init__.py
datus_snowflake/config.py
datus_snowflake/connector.py
datus_snowflake-0.1.0.dist-info/METADATA
datus_snowflake-0.1.0.dist-info/WHEEL
datus_snowflake-0.1.0.dist-info/entry_points.txt
datus_snowflake-0.1.0.dist-info/RECORD
