Metadata-Version: 2.4
Name: datus-snowflake
Version: 0.1.0
Summary: Snowflake adapter for Datus Agent
Author-email: DatusAI <support@datus.ai>
License: Apache-2.0
Requires-Python: >=3.8
Requires-Dist: datus-agent>0.2.1
Requires-Dist: snowflake-connector-python>=3.6.0
Provides-Extra: dev
Requires-Dist: pytest-cov>=4.0.0; extra == 'dev'
Requires-Dist: pytest>=7.0.0; extra == 'dev'
